{
	"pages": [ //pages数组中第一项表示应用启动页，参考：https://uniapp.dcloud.io/collocation/pages
		{
			"path": "pages/tabbar/index/index",
			"style": {
				"navigationBarTitleText": "我的微信"
			}
		},
		{
			"path": "pages/tabbar/mail/mail",
			"style": {
				"navigationBarTitleText": "我的微信"
			}
		},
		{
			"path": "pages/tabbar/find/find",
			"style": {
				"navigationBarTitleText": "我的微信"
			}
		},
		{
			"path": "pages/tabbar/my/my",
			"style": {
				"navigationBarTitleText": "我的微信"
			}
		}
	],
	"globalStyle": {
		"navigationBarTextStyle": "black",
		"navigationBarTitleText": "",
		"navigationBarBackgroundColor": "#F8F8F8",
		"backgroundColor": "#F8F8F8",
		"app-plus": {
			"titleNView": false,
			"scrollIndicator": "none"
		}
	},
	"tabBar": {
		"borderStyle": "black",
		"backgroundColor": "#F7F7F7",
		"color": "#000000",
		"selectedColor": "#08C261",
		"list": [
			{
				"iconPath": "static/tabbar/index.png",
				"selectedIconPath": "static/tabbar/index-select.png",
				"text": "首页",
				"pagePath": "pages/tabbar/index/index"
			},
			{
				"iconPath": "static/tabbar/mail.png",
				"selectedIconPath": "static/tabbar/mail-select.png",
				"text": "通讯录",
				"pagePath": "pages/tabbar/mail/mail"
			},
			{
				"iconPath": "static/tabbar/find.png",
				"selectedIconPath": "static/tabbar/find-select.png",
				"text": "发现",
				"pagePath": "pages/tabbar/find/find"
			},
			{
				"iconPath": "static/tabbar/my.png",
				"selectedIconPath": "static/tabbar/my-select.png",
				"text": "我的",
				"pagePath": "pages/tabbar/my/my"
			}
		]
	}
}